{"Response":{"informationType":"METERED_INJECTIONS","period.timeInterval":{"start":"2025-01-27T00:00","end":"2025-01-28T00:00"},"conversation_id":null,"TimeSeries":[{"mRID":1,"quantity_Measurement_Unit_name":"MWh","Period":{"timeInterval":{"start":"2025-01-27T00:00","end":"2025-01-28T00:00"},"Points":[{"timeInterval_start":"2025-01-27T00:00","timeInterval_end":"2025-01-27T00:15","isp":"1","measured_infeed":"2122.328","scheduled_import":"97.850","scheduled_export":"-473.700"},{"timeInterval_start":"2025-01-27T00:15","timeInterval_end":"2025-01-27T00:30","isp":"2","measured_infeed":"2071.419","scheduled_import":"97.600","scheduled_export":"-467.075"},{"timeInterval_start":"2025-01-27T00:30","timeInterval_end":"2025-01-27T00:45","isp":"3","measured_infeed":"2061.243","scheduled_import":"97.675","scheduled_export":"-467.475"},{"timeInterval_start":"2025-01-27T00:45","timeInterval_end":"2025-01-27T01:00","isp":"4","measured_infeed":"2026.480","scheduled_import":"97.725","scheduled_export":"-466.925"},{"timeInterval_start":"2025-01-27T01:00","timeInterval_end":"2025-01-27T01:15","isp":"5","measured_infeed":"2027.554","scheduled_import":"98.075","scheduled_export":"-514.700"},{"timeInterval_start":"2025-01-27T01:15","timeInterval_end":"2025-01-27T01:30","isp":"6","measured_infeed":"1983.471","scheduled_import":"97.825","scheduled_export":"-505.450"},{"timeInterval_start":"2025-01-27T01:30","timeInterval_end":"2025-01-27T01:45","isp":"7","measured_infeed":"2008.791","scheduled_import":"97.925","scheduled_export":"-507.125"},{"timeInterval_start":"2025-01-27T01:45","timeInterval_end":"2025-01-27T02:00","isp":"8","measured_infeed":"1987.799","scheduled_import":"97.925","scheduled_export":"-501.550"},{"timeInterval_start":"2025-01-27T02:00","timeInterval_end":"2025-01-27T02:15","isp":"9","measured_infeed":"1958.176","scheduled_import":"152.450","scheduled_export":"-637.175"},{"timeInterval_start":"2025-01-27T02:15","timeInterval_end":"2025-01-27T02:30","isp":"10","measured_infeed":"1963.535","scheduled_import":"161.700","scheduled_export":"-638.425"},{"timeInterval_start":"2025-01-27T02:30","timeInterval_end":"2025-01-27T02:45","isp":"11","measured_infeed":"1954.411","scheduled_import":"162.675","scheduled_export":"-637.175"},{"timeInterval_start":"2025-01-27T02:45","timeInterval_end":"2025-01-27T03:00","isp":"12","measured_infeed":"1914.795","scheduled_import":"162.525","scheduled_export":"-637.025"},{"timeInterval_start":"2025-01-27T03:00","timeInterval_end":"2025-01-27T03:15","isp":"13","measured_infeed":"1883.791","scheduled_import":"120.825","scheduled_export":"-716.950"},{"timeInterval_start":"2025-01-27T03:15","timeInterval_end":"2025-01-27T03:30","isp":"14","measured_infeed":"1887.451","scheduled_import":"120.825","scheduled_export":"-716.950"},{"timeInterval_start":"2025-01-27T03:30","timeInterval_end":"2025-01-27T03:45","isp":"15","measured_infeed":"1856.153","scheduled_import":"121.325","scheduled_export":"-720.500"},{"timeInterval_start":"2025-01-27T03:45","timeInterval_end":"2025-01-27T04:00","isp":"16","measured_infeed":"1866.058","scheduled_import":"121.325","scheduled_export":"-718.825"},{"timeInterval_start":"2025-01-27T04:00","timeInterval_end":"2025-01-27T04:15","isp":"17","measured_infeed":"1860.108","scheduled_import":"62.350","scheduled_export":"-656.125"},{"timeInterval_start":"2025-01-27T04:15","timeInterval_end":"2025-01-27T04:30","isp":"18","measured_infeed":"1892.389","scheduled_import":"59.400","scheduled_export":"-656.000"},{"timeInterval_start":"2025-01-27T04:30","timeInterval_end":"2025-01-27T04:45","isp":"19","measured_infeed":"1839.953","scheduled_import":"56.475","scheduled_export":"-655.225"},{"timeInterval_start":"2025-01-27T04:45","timeInterval_end":"2025-01-27T05:00","isp":"20","measured_infeed":"1889.898","scheduled_import":"54.025","scheduled_export":"-655.925"},{"timeInterval_start":"2025-01-27T05:00","timeInterval_end":"2025-01-27T05:15","isp":"21","measured_infeed":"1927.172","scheduled_import":"68.775","scheduled_export":"-597.250"},{"timeInterval_start":"2025-01-27T05:15","timeInterval_end":"2025-01-27T05:30","isp":"22","measured_infeed":"1919.910","scheduled_import":"68.775","scheduled_export":"-597.875"},{"timeInterval_start":"2025-01-27T05:30","timeInterval_end":"2025-01-27T05:45","isp":"23","measured_infeed":"1981.760","scheduled_import":"68.575","scheduled_export":"-600.700"},{"timeInterval_start":"2025-01-27T05:45","timeInterval_end":"2025-01-27T06:00","isp":"24","measured_infeed":"1977.444","scheduled_import":"68.725","scheduled_export":"-606.725"},{"timeInterval_start":"2025-01-27T06:00","timeInterval_end":"2025-01-27T06:15","isp":"25","measured_infeed":"2157.773","scheduled_import":"77.825","scheduled_export":"-388.575"},{"timeInterval_start":"2025-01-27T06:15","timeInterval_end":"2025-01-27T06:30","isp":"26","measured_infeed":"2213.900","scheduled_import":"77.600","scheduled_export":"-388.600"},{"timeInterval_start":"2025-01-27T06:30","timeInterval_end":"2025-01-27T06:45","isp":"27","measured_infeed":"2281.597","scheduled_import":"77.725","scheduled_export":"-397.250"},{"timeInterval_start":"2025-01-27T06:45","timeInterval_end":"2025-01-27T07:00","isp":"28","measured_infeed":"2351.447","scheduled_import":"77.500","scheduled_export":"-405.700"},{"timeInterval_start":"2025-01-27T07:00","timeInterval_end":"2025-01-27T07:15","isp":"29","measured_infeed":"2571.242","scheduled_import":"338.300","scheduled_export":"-187.225"},{"timeInterval_start":"2025-01-27T07:15","timeInterval_end":"2025-01-27T07:30","isp":"30","measured_infeed":"2665.303","scheduled_import":"338.300","scheduled_export":"-175.700"},{"timeInterval_start":"2025-01-27T07:30","timeInterval_end":"2025-01-27T07:45","isp":"31","measured_infeed":"2804.134","scheduled_import":"334.500","scheduled_export":"-167.725"},{"timeInterval_start":"2025-01-27T07:45","timeInterval_end":"2025-01-27T08:00","isp":"32","measured_infeed":"2791.985","scheduled_import":"334.500","scheduled_export":"-165.975"},{"timeInterval_start":"2025-01-27T08:00","timeInterval_end":"2025-01-27T08:15","isp":"33","measured_infeed":"2915.490","scheduled_import":"544.575","scheduled_export":"-136.625"},{"timeInterval_start":"2025-01-27T08:15","timeInterval_end":"2025-01-27T08:30","isp":"34","measured_infeed":"2936.200","scheduled_import":"544.575","scheduled_export":"-136.625"},{"timeInterval_start":"2025-01-27T08:30","timeInterval_end":"2025-01-27T08:45","isp":"35","measured_infeed":"3023.032","scheduled_import":"544.575","scheduled_export":"-136.375"},{"timeInterval_start":"2025-01-27T08:45","timeInterval_end":"2025-01-27T09:00","isp":"36","measured_infeed":"3005.786","scheduled_import":"544.575","scheduled_export":"-136.375"},{"timeInterval_start":"2025-01-27T09:00","timeInterval_end":"2025-01-27T09:15","isp":"37","measured_infeed":"2995.122","scheduled_import":"458.675","scheduled_export":"-105.750"},{"timeInterval_start":"2025-01-27T09:15","timeInterval_end":"2025-01-27T09:30","isp":"38","measured_infeed":"2896.605","scheduled_import":"458.625","scheduled_export":"-115.525"},{"timeInterval_start":"2025-01-27T09:30","timeInterval_end":"2025-01-27T09:45","isp":"39","measured_infeed":"2794.639","scheduled_import":"458.600","scheduled_export":"-126.125"},{"timeInterval_start":"2025-01-27T09:45","timeInterval_end":"2025-01-27T10:00","isp":"40","measured_infeed":"2732.296","scheduled_import":"458.625","scheduled_export":"-125.025"},{"timeInterval_start":"2025-01-27T10:00","timeInterval_end":"2025-01-27T10:15","isp":"41","measured_infeed":"2615.251","scheduled_import":"448.325","scheduled_export":"-297.050"},{"timeInterval_start":"2025-01-27T10:15","timeInterval_end":"2025-01-27T10:30","isp":"42","measured_infeed":"2463.097","scheduled_import":"448.150","scheduled_export":"-302.450"},{"timeInterval_start":"2025-01-27T10:30","timeInterval_end":"2025-01-27T10:45","isp":"43","measured_infeed":"2321.724","scheduled_import":"448.150","scheduled_export":"-297.725"},{"timeInterval_start":"2025-01-27T10:45","timeInterval_end":"2025-01-27T11:00","isp":"44","measured_infeed":"2217.967","scheduled_import":"448.150","scheduled_export":"-299.700"},{"timeInterval_start":"2025-01-27T11:00","timeInterval_end":"2025-01-27T11:15","isp":"45","measured_infeed":"2026.934","scheduled_import":"168.850","scheduled_export":"-401.675"},{"timeInterval_start":"2025-01-27T11:15","timeInterval_end":"2025-01-27T11:30","isp":"46","measured_infeed":"2056.488","scheduled_import":"168.725","scheduled_export":"-407.800"},{"timeInterval_start":"2025-01-27T11:30","timeInterval_end":"2025-01-27T11:45","isp":"47","measured_infeed":"1996.800","scheduled_import":"168.725","scheduled_export":"-402.350"},{"timeInterval_start":"2025-01-27T11:45","timeInterval_end":"2025-01-27T12:00","isp":"48","measured_infeed":"1963.530","scheduled_import":"169.900","scheduled_export":"-401.350"},{"timeInterval_start":"2025-01-27T12:00","timeInterval_end":"2025-01-27T12:15","isp":"49","measured_infeed":"1749.590","scheduled_import":"215.950","scheduled_export":"-994.075"},{"timeInterval_start":"2025-01-27T12:15","timeInterval_end":"2025-01-27T12:30","isp":"50","measured_infeed":"1712.335","scheduled_import":"215.900","scheduled_export":"-987.725"},{"timeInterval_start":"2025-01-27T12:30","timeInterval_end":"2025-01-27T12:45","isp":"51","measured_infeed":"1646.921","scheduled_import":"216.075","scheduled_export":"-989.300"},{"timeInterval_start":"2025-01-27T12:45","timeInterval_end":"2025-01-27T13:00","isp":"52","measured_infeed":"1651.148","scheduled_import":"216.075","scheduled_export":"-985.625"},{"timeInterval_start":"2025-01-27T13:00","timeInterval_end":"2025-01-27T13:15","isp":"53","measured_infeed":"1580.590","scheduled_import":"228.225","scheduled_export":"-984.300"},{"timeInterval_start":"2025-01-27T13:15","timeInterval_end":"2025-01-27T13:30","isp":"54","measured_infeed":"1688.601","scheduled_import":"228.225","scheduled_export":"-980.650"},{"timeInterval_start":"2025-01-27T13:30","timeInterval_end":"2025-01-27T13:45","isp":"55","measured_infeed":"1714.452","scheduled_import":"228.225","scheduled_export":"-980.875"},{"timeInterval_start":"2025-01-27T13:45","timeInterval_end":"2025-01-27T14:00","isp":"56","measured_infeed":"1740.475","scheduled_import":"228.225","scheduled_export":"-983.200"},{"timeInterval_start":"2025-01-27T14:00","timeInterval_end":"2025-01-27T14:15","isp":"57","measured_infeed":"1750.928","scheduled_import":"163.650","scheduled_export":"-888.650"},{"timeInterval_start":"2025-01-27T14:15","timeInterval_end":"2025-01-27T14:30","isp":"58","measured_infeed":"1804.558","scheduled_import":"163.650","scheduled_export":"-894.075"},{"timeInterval_start":"2025-01-27T14:30","timeInterval_end":"2025-01-27T14:45","isp":"59","measured_infeed":"1798.071","scheduled_import":"163.650","scheduled_export":"-902.175"},{"timeInterval_start":"2025-01-27T14:45","timeInterval_end":"2025-01-27T15:00","isp":"60","measured_infeed":"1856.162","scheduled_import":"163.650","scheduled_export":"-905.475"},{"timeInterval_start":"2025-01-27T15:00","timeInterval_end":"2025-01-27T15:15","isp":"61","measured_infeed":"2048.699","scheduled_import":"281.000","scheduled_export":"-666.500"},{"timeInterval_start":"2025-01-27T15:15","timeInterval_end":"2025-01-27T15:30","isp":"62","measured_infeed":"2093.627","scheduled_import":"281.000","scheduled_export":"-666.500"},{"timeInterval_start":"2025-01-27T15:30","timeInterval_end":"2025-01-27T15:45","isp":"63","measured_infeed":"2246.250","scheduled_import":"280.650","scheduled_export":"-669.725"},{"timeInterval_start":"2025-01-27T15:45","timeInterval_end":"2025-01-27T16:00","isp":"64","measured_infeed":"2327.549","scheduled_import":"280.650","scheduled_export":"-672.875"},{"timeInterval_start":"2025-01-27T16:00","timeInterval_end":"2025-01-27T16:15","isp":"65","measured_infeed":"2538.768","scheduled_import":"185.325","scheduled_export":"-91.775"},{"timeInterval_start":"2025-01-27T16:15","timeInterval_end":"2025-01-27T16:30","isp":"66","measured_infeed":"2687.150","scheduled_import":"185.325","scheduled_export":"-94.500"},{"timeInterval_start":"2025-01-27T16:30","timeInterval_end":"2025-01-27T16:45","isp":"67","measured_infeed":"2847.823","scheduled_import":"185.150","scheduled_export":"-94.750"},{"timeInterval_start":"2025-01-27T16:45","timeInterval_end":"2025-01-27T17:00","isp":"68","measured_infeed":"2932.163","scheduled_import":"185.150","scheduled_export":"-100.975"},{"timeInterval_start":"2025-01-27T17:00","timeInterval_end":"2025-01-27T17:15","isp":"69","measured_infeed":"3012.795","scheduled_import":"317.200","scheduled_export":"-141.025"},{"timeInterval_start":"2025-01-27T17:15","timeInterval_end":"2025-01-27T17:30","isp":"70","measured_infeed":"3135.128","scheduled_import":"317.200","scheduled_export":"-140.550"},{"timeInterval_start":"2025-01-27T17:30","timeInterval_end":"2025-01-27T17:45","isp":"71","measured_infeed":"3141.486","scheduled_import":"317.100","scheduled_export":"-140.650"},{"timeInterval_start":"2025-01-27T17:45","timeInterval_end":"2025-01-27T18:00","isp":"72","measured_infeed":"3147.830","scheduled_import":"317.100","scheduled_export":"-140.650"},{"timeInterval_start":"2025-01-27T18:00","timeInterval_end":"2025-01-27T18:15","isp":"73","measured_infeed":"3052.988","scheduled_import":"236.400","scheduled_export":"-257.625"},{"timeInterval_start":"2025-01-27T18:15","timeInterval_end":"2025-01-27T18:30","isp":"74","measured_infeed":"2987.143","scheduled_import":"236.400","scheduled_export":"-265.800"},{"timeInterval_start":"2025-01-27T18:30","timeInterval_end":"2025-01-27T18:45","isp":"75","measured_infeed":"2966.745","scheduled_import":"236.400","scheduled_export":"-292.025"},{"timeInterval_start":"2025-01-27T18:45","timeInterval_end":"2025-01-27T19:00","isp":"76","measured_infeed":"2946.496","scheduled_import":"236.500","scheduled_export":"-286.000"},{"timeInterval_start":"2025-01-27T19:00","timeInterval_end":"2025-01-27T19:15","isp":"77","measured_infeed":"2927.160","scheduled_import":"204.875","scheduled_export":"-254.200"},{"timeInterval_start":"2025-01-27T19:15","timeInterval_end":"2025-01-27T19:30","isp":"78","measured_infeed":"2861.933","scheduled_import":"204.875","scheduled_export":"-249.400"},{"timeInterval_start":"2025-01-27T19:30","timeInterval_end":"2025-01-27T19:45","isp":"79","measured_infeed":"2805.170","scheduled_import":"205.050","scheduled_export":"-249.325"},{"timeInterval_start":"2025-01-27T19:45","timeInterval_end":"2025-01-27T20:00","isp":"80","measured_infeed":"2788.653","scheduled_import":"205.225","scheduled_export":"-249.250"},{"timeInterval_start":"2025-01-27T20:00","timeInterval_end":"2025-01-27T20:15","isp":"81","measured_infeed":"2668.088","scheduled_import":"215.475","scheduled_export":"-341.375"},{"timeInterval_start":"2025-01-27T20:15","timeInterval_end":"2025-01-27T20:30","isp":"82","measured_infeed":"2628.931","scheduled_import":"215.475","scheduled_export":"-341.375"},{"timeInterval_start":"2025-01-27T20:30","timeInterval_end":"2025-01-27T20:45","isp":"83","measured_infeed":"2581.646","scheduled_import":"215.675","scheduled_export":"-341.250"},{"timeInterval_start":"2025-01-27T20:45","timeInterval_end":"2025-01-27T21:00","isp":"84","measured_infeed":"2550.305","scheduled_import":"215.675","scheduled_export":"-341.075"},{"timeInterval_start":"2025-01-27T21:00","timeInterval_end":"2025-01-27T21:15","isp":"85","measured_infeed":"2533.956","scheduled_import":"162.775","scheduled_export":"-320.500"},{"timeInterval_start":"2025-01-27T21:15","timeInterval_end":"2025-01-27T21:30","isp":"86","measured_infeed":"2477.061","scheduled_import":"162.775","scheduled_export":"-314.325"},{"timeInterval_start":"2025-01-27T21:30","timeInterval_end":"2025-01-27T21:45","isp":"87","measured_infeed":"2488.533","scheduled_import":"162.900","scheduled_export":"-313.825"},{"timeInterval_start":"2025-01-27T21:45","timeInterval_end":"2025-01-27T22:00","isp":"88","measured_infeed":"2427.549","scheduled_import":"162.900","scheduled_export":"-313.825"},{"timeInterval_start":"2025-01-27T22:00","timeInterval_end":"2025-01-27T22:15","isp":"89","measured_infeed":"2345.988","scheduled_import":"173.500","scheduled_export":"-491.750"},{"timeInterval_start":"2025-01-27T22:15","timeInterval_end":"2025-01-27T22:30","isp":"90","measured_infeed":"2283.350","scheduled_import":"173.500","scheduled_export":"-495.175"},{"timeInterval_start":"2025-01-27T22:30","timeInterval_end":"2025-01-27T22:45","isp":"91","measured_infeed":"2234.547","scheduled_import":"173.500","scheduled_export":"-494.050"},{"timeInterval_start":"2025-01-27T22:45","timeInterval_end":"2025-01-27T23:00","isp":"92","measured_infeed":"2236.510","scheduled_import":"173.500","scheduled_export":"-492.400"},{"timeInterval_start":"2025-01-27T23:00","timeInterval_end":"2025-01-27T23:15","isp":"93","measured_infeed":"2172.330","scheduled_import":"155.000","scheduled_export":"-553.600"},{"timeInterval_start":"2025-01-27T23:15","timeInterval_end":"2025-01-27T23:30","isp":"94","measured_infeed":"2113.121","scheduled_import":"155.000","scheduled_export":"-549.225"},{"timeInterval_start":"2025-01-27T23:30","timeInterval_end":"2025-01-27T23:45","isp":"95","measured_infeed":"2129.278","scheduled_import":"155.000","scheduled_export":"-548.150"},{"timeInterval_start":"2025-01-27T23:45","timeInterval_end":"2025-01-28T00:00","isp":"96","measured_infeed":"2082.808","scheduled_import":"155.000","scheduled_export":"-548.150"}]}}]}}